gns3_server-3.0.5.dist-info/licenses/LICENSE
gns3server/__init__.py
gns3server/__main__.py
gns3server/alembic.ini
gns3server/config.py
gns3server/crash_report.py
gns3server/logger.py
gns3server/main.py
gns3server/server.py
gns3server/version.py
gns3server/api/__init__.py
gns3server/api/server.py
gns3server/api/routes/__init__.py
gns3server/api/routes/index.py
gns3server/api/routes/compute/__init__.py
gns3server/api/routes/compute/atm_switch_nodes.py
gns3server/api/routes/compute/capabilities.py
gns3server/api/routes/compute/cloud_nodes.py
gns3server/api/routes/compute/compute.py
gns3server/api/routes/compute/docker_nodes.py
gns3server/api/routes/compute/dynamips_nodes.py
gns3server/api/routes/compute/ethernet_hub_nodes.py
gns3server/api/routes/compute/ethernet_switch_nodes.py
gns3server/api/routes/compute/frame_relay_switch_nodes.py
gns3server/api/routes/compute/images.py
gns3server/api/routes/compute/iou_nodes.py
gns3server/api/routes/compute/nat_nodes.py
gns3server/api/routes/compute/notifications.py
gns3server/api/routes/compute/projects.py
gns3server/api/routes/compute/qemu_nodes.py
gns3server/api/routes/compute/virtualbox_nodes.py
gns3server/api/routes/compute/vmware_nodes.py
gns3server/api/routes/compute/vpcs_nodes.py
gns3server/api/routes/compute/dependencies/__init__.py
gns3server/api/routes/compute/dependencies/authentication.py
gns3server/api/routes/controller/__init__.py
gns3server/api/routes/controller/acl.py
gns3server/api/routes/controller/appliances.py
gns3server/api/routes/controller/computes.py
gns3server/api/routes/controller/controller.py
gns3server/api/routes/controller/drawings.py
gns3server/api/routes/controller/gns3vm.py
gns3server/api/routes/controller/groups.py
gns3server/api/routes/controller/images.py
gns3server/api/routes/controller/links.py
gns3server/api/routes/controller/nodes.py
gns3server/api/routes/controller/pools.py
gns3server/api/routes/controller/privileges.py
gns3server/api/routes/controller/projects.py
gns3server/api/routes/controller/roles.py
gns3server/gns3_server.egg-info/PKG-INFO
gns3server/gns3_server.egg-info/SOURCES.txt
gns3server/gns3_server.egg-info/dependency_links.txt
gns3server/gns3_server.egg-info/entry_points.txt
gns3server/gns3_server.egg-info/not-zip-safe
gns3server/gns3_server.egg-info/requires.txt
gns3server/gns3_server.egg-info/top_level.txt
gns3_server-3.0.5.dist-info/METADATA
gns3_server-3.0.5.dist-info/WHEEL
gns3_server-3.0.5.dist-info/entry_points.txt
gns3_server-3.0.5.dist-info/top_level.txt
gns3_server-3.0.5.dist-info/RECORD
