Metadata-Version: 2.4
Name: gns3-server
Version: 3.0.5
Summary: GNS3 graphical interface for the GNS3 server.
Author-email: Jeremy Grossmann <developers@gns3.com>
Project-URL: Homepage, http://gns3.com
Project-URL: Repository, http://github.com/GNS3/gns3-server
Project-URL: Bug tracker, http://github.com/GNS3/gns3-server/issues
Classifier: Development Status :: 5 - Production/Stable
Classifier: Environment :: Console
Classifier: Framework :: FastAPI
Classifier: Intended Audience :: Information Technology
Classifier: Topic :: System :: Networking
Classifier: License :: OSI Approved :: GNU General Public License v3 (GPLv3)
Classifier: Natural Language :: English
Classifier: Operating System :: POSIX :: Linux
Classifier: Programming Language :: Python :: 3 :: Only
Classifier: Programming Language :: Python :: 3.9
Classifier: Programming Language :: Python :: 3.10
Classifier: Programming Language :: Python :: 3.11
Classifier: Programming Language :: Python :: 3.12
Classifier: Programming Language :: Python :: 3.13
Classifier: Programming Language :: Python :: Implementation :: CPython
Requires-Python: >=3.9
License-File: LICENSE
Requires-Dist: uvicorn==0.34.2
Requires-Dist: pydantic==2.11.4
Requires-Dist: fastapi==0.115.12
Requires-Dist: python-multipart==0.0.20
Requires-Dist: websockets==15.0.1
Requires-Dist: aiohttp<3.12,>=3.11.16
Requires-Dist: async-timeout==5.0.1; python_version < "3.11"
Requires-Dist: aiofiles<25.0,>=24.1.0
Requires-Dist: Jinja2<3.2,>=3.1.6
Requires-Dist: sentry-sdk<2.27,>=2.26.1
Requires-Dist: psutil>=7.0.0
Requires-Dist: async-timeout<5.1,>=5.0.1
Requires-Dist: distro>=1.9.0
Requires-Dist: py-cpuinfo<10.0,>=9.0.0
Requires-Dist: greenlet==3.2.0
Requires-Dist: sqlalchemy==2.0.40
Requires-Dist: aiosqlite==0.21.0
Requires-Dist: alembic==1.15.2
Requires-Dist: bcrypt==4.3.0
Requires-Dist: joserfc==1.0.4
Requires-Dist: email-validator==2.2.0
Requires-Dist: watchdog==6.0.0
Requires-Dist: zstandard==0.23.0
Requires-Dist: platformdirs<3,>=2.4.0
Requires-Dist: importlib-resources>=1.3; python_version <= "3.9"
Requires-Dist: truststore>=0.10.1; python_version >= "3.10"
Provides-Extra: dev
Requires-Dist: pytest==8.3.4; extra == "dev"
Requires-Dist: flake8==7.1.1; extra == "dev"
Requires-Dist: pytest-timeout==2.3.1; extra == "dev"
Requires-Dist: pytest-asyncio==0.25.2; extra == "dev"
Requires-Dist: requests==2.32.3; extra == "dev"
Requires-Dist: httpx==0.28.1; extra == "dev"
Requires-Dist: httpx_ws==0.7.1; extra == "dev"
Dynamic: license-file
